{
  "unversionedId": "home/congratulations",
  "id": "home/congratulations",
  "title": "Congratulations!",
  "description": "You have just learned the basics of Docusaurus and made some changes to the initial template.",
  "source": "@site/docs/home/congratulations.md",
  "sourceDirName": "home",
  "slug": "/home/congratulations",
  "permalink": "/edc-docs/docs/home/congratulations",
  "draft": false,
  "editUrl": "https://github.com/eclipse-dataspacecomponents/docs/tree/main/docs/docs/home/congratulations.md",
  "tags": [],
  "version": "current",
  "sidebarPosition": 6,
  "frontMatter": {
    "sidebar_position": 6
  },
  "sidebar": "tutorialSidebar",
  "previous": {
    "title": "Deploy your site",
    "permalink": "/edc-docs/docs/home/deploy-your-site"
  },
  "next": {
    "title": "Tutorial - Extras",
    "permalink": "/edc-docs/docs/category/tutorial---extras"
  }
}